wikipedia_tool/__init__.py
wikipedia_tool-1.0.0.dist-info/LICENSE
wikipedia_tool-1.0.0.dist-info/METADATA
wikipedia_tool-1.0.0.dist-info/WHEEL
wikipedia_tool-1.0.0.dist-info/top_level.txt
wikipedia_tool-1.0.0.dist-info/RECORD
